senseqnet/SenSeqNet_model.pth
senseqnet/__init__.py
senseqnet/cli.py
senseqnet/inference.py
senseqnet/models.py
senseqnet/data/negative_0.4.fasta
senseqnet/data/positive_0.4.fasta
senseqnet/data/reps_30_rep_seq_neg.fasta
senseqnet/data/reps_30_rep_seq_pos.fasta
senseqnet-1.1.2.dist-info/METADATA
senseqnet-1.1.2.dist-info/WHEEL
senseqnet-1.1.2.dist-info/entry_points.txt
senseqnet-1.1.2.dist-info/top_level.txt
senseqnet-1.1.2.dist-info/RECORD
