Metadata-Version: 2.4
Name: senseqnet
Version: 1.1.2
Summary: A Deep Learning Framework for Cellular Senescence Detection from Protein Sequences
Home-page: https://github.com/HanliJiang13/SenSeqNet_Package
Author: Hanli Jiang
Author-email: hhanlijiang@mail.utoronto.ca
Classifier: Programming Language :: Python :: 3
Classifier: Operating System :: OS Independent
Requires-Python: >=3.7
Requires-Dist: torch>=1.10.0
Requires-Dist: numpy
Requires-Dist: pandas
Requires-Dist: biopython
Requires-Dist: click
Requires-Dist: fair-esm
Dynamic: author
Dynamic: author-email
Dynamic: classifier
Dynamic: description-content-type
Dynamic: home-page
Dynamic: requires-dist
Dynamic: requires-python
Dynamic: summary
